{
	"format_version": "1.8.0",
	"minecraft:client_entity": {
		"description": {
			"identifier": "horizon:basic_disk",
			"materials": {
				"default": "entity_alphatest"
			},
			"textures": {
				"default": "textures/entity/disk_1"
			},
			"geometry": {
				"default": "geometry.basic_disk"
			},
			"render_controllers": [
				"controller.render.basic_disk"
			],
			"animations": {
				"walk": "animation.horizon.disk_basic.rotation"
			},
			"animation_controllers": [
				{
					"walk": "controller.animation.horizon_basic_disk"
				}
			]
		}
	}
}